inskrib
