Metadata-Version: 2.1
Name: inskrib
Version: 0.0.1.6
Summary: Inskrib - simple library for getting signature from docs
Home-page: https://github.com/ElishaFlacon/inskrib
Download-URL: https://github.com/ElishaFlacon/inskrib/archive/main.zip
Author: Elisha Flacon
License: BSD 3-Clause
Classifier: License :: OSI Approved :: BSD License
Classifier: Intended Audience :: Developers
Classifier: Programming Language :: Python :: 3.8
Classifier: Programming Language :: Python :: 3.9
Classifier: Programming Language :: Python :: 3.10
Requires-Python: >=3.8
License-File: LICENSE
